{
    "component": {
        "build": {
            "inner_kits": [
                {
                    "header": {
                        "header_base": "//third_party/asmjit",
                        "header_files": ""
                    },
                    "name": "//arkcompiler/toolchain/build/third_party_gn/asmjit:libasmjit"
                },
                {
                    "header": {
                        "header_base": "//third_party/zlib",
                        "header_files": ""
                    },
                    "name": "//arkcompiler/toolchain/build/third_party_gn/asmjit:libasmjit_frontend_static"
                }
            ]
        }
    }
}
